pycomposite/__init__.py
pycomposite/composite_decorator.py
pycomposite-1.0.2.dist-info/LICENSE.md
pycomposite-1.0.2.dist-info/WHEEL
pycomposite-1.0.2.dist-info/METADATA
pycomposite-1.0.2.dist-info/RECORD
