Metadata-Version: 2.1
Name: pycomposite
Version: 1.0.2
Summary: Generic implementation of the Composite Design Pattern as a Python class decorator.
Author-email: BST Labs <bstlabs@caios.io>
Requires-Python: >=3.8
Classifier: License :: OSI Approved :: MIT License
Requires-Dist: deepmerge >= 1.1.0
Requires-Dist: black >=22.3.0 ; extra == "dev"
Requires-Dist: pylint >=2.12.2 ; extra == "dev"
Requires-Dist: isort >=5.9.3 ; extra == "dev"
Requires-Dist: autoflake >=1.4 ; extra == "dev"
Requires-Dist: flake8 >=4.0.1 ; extra == "dev"
Requires-Dist: pre-commit >=2.17.0 ; extra == "dev"
Requires-Dist: mkdocs-material >=8.1.2 ; extra == "doc"
Project-URL: Documentation, https://bstlabs.github.io/py-composite
Project-URL: Home, https://bstlabs.github.io/py-composite
Project-URL: Source, https://github.com/bstlabs/py-composite
Provides-Extra: dev
Provides-Extra: doc
